{
  "language": "Solidity",
  "sources": {
    "contracts/BasicFDT.sol": {
      "urls": ["contracts/BasicFDT.sol"]
    },
    "contracts/BasicFundsTokenFDT.sol": {
      "urls": ["contracts/BasicFundsTokenFDT.sol"]
    },
    "contracts/ExtendedFDT.sol": {
      "urls": ["contracts/ExtendedFDT.sol"]
    },
    "contracts/test/BasicFDT.t.sol": {
      "urls": ["contracts/test/BasicFDT.t.sol"]
    },
    "contracts/test/BasicFundsTokenFDT.t.sol": {
      "urls": ["contracts/test/BasicFundsTokenFDT.t.sol"]
    },
    "contracts/test/ExtendedFDT.t.sol": {
      "urls": ["contracts/test/ExtendedFDT.t.sol"]
    }
  },
  "settings": {
    "optimizer": {
      "enabled": true,
      "runs": 200
    },
    "outputSelection": {
      "*": {
        "*": [
          "abi",
          "evm.bytecode",
          "evm.deployedBytecode"
        ],
        "": ["ast"]
      }
    },
    "metadata": {
      "bytecodeHash": "none"
    }
  }
}
